fb_duckling/__init__.py
fb_duckling/anonymizer.py
fb_duckling/base_class.py
fb_duckling/duckling.py
fb_duckling/utils.py
fb_duckling-1.0.dist-info/AUTHORS.rst
fb_duckling-1.0.dist-info/LICENSE.txt
fb_duckling-1.0.dist-info/METADATA
fb_duckling-1.0.dist-info/WHEEL
fb_duckling-1.0.dist-info/dependency_links.txt
fb_duckling-1.0.dist-info/entry_points.txt
fb_duckling-1.0.dist-info/top_level.txt
fb_duckling-1.0.dist-info/RECORD
