Metadata-Version: 2.1
Name: fb-duckling
Version: 1.0
Summary: A python wrapper for facebook s duckling.
Home-page: https://github.com/duckling-python-wrapper/fb_duckling
Author: Benjamin Breton
Author-email: benjamin.breton45@gmail.com
License: mit
Platform: any
Classifier: Development Status :: 4 - Beta
Classifier: Programming Language :: Python
